{"_id":{"$oid":"6672ba62f1b1186875c52ac6"},"MaHD":"HD001","NgayLap":{"$date":"2024-06-19T11:00:50.579Z"},"KhachHang":{"MaKH":"KH001","TenKH":"Lê Thị Hoa","DiaChi":"Bình Thạnh, TP.HCM"},"SanPham":[{"MaSP":"SP001","TenSP":"Nồi nấu lẩu","SoLuong":1,"GiaBan":299000,"ThanhTien":299000},{"MaSP":"SP005","TenSP":"Chảo chống dính bán kính 50cm","SoLuong":2,"GiaBan":150000,"ThanhTien":300000}]}
{"_id":{"$oid":"6672bba5f1b1186875c52ac7"},"MaHD":"HD002","NgayLap":{"$date":"2024-06-19T11:06:13.565Z"},"KhachHang":{"MaKH":"KH002","TenKH":"Trần Minh Tuấn","DiaChi":"Tân Phú, TP.HCM"},"SanPham":[{"MaSP":"SP002","TenSP":"Quạt điện","SoLuong":1,"GiaBan":399000,"ThanhTien":399000},{"MaSP":"SP005","TenSP":"Chảo chống dính bán kính 50cm","SoLuong":1,"GiaBan":150000,"ThanhTien":150000}]}
{"_id":{"$oid":"6672bba5f1b1186875c52ac8"},"MaHD":"HD003","NgayLap":{"$date":"2024-06-19T11:06:13.565Z"},"KhachHang":{"MaKH":"KH003","TenKH":"Nguyễn Ngọc Lan Anh","DiaChi":"Bình Dương"},"SanPham":[{"MaSP":"SP003","TenSP":"Chảo gang bán kính 40cm","SoLuong":1,"GiaBan":179000,"ThanhTien":179000},{"MaSP":"SP005","TenSP":"Chảo chống dính bán kính 50cm","SoLuong":1,"GiaBan":150000,"ThanhTien":150000}]}
{"_id":{"$oid":"6672bda5f1b1186875c52ac9"},"MaHD":"H001","NgayLap":{"$date":"2020-04-01T00:00:01.993Z"},"KhachHang":{"MaKH":"KH001","TenKH":"Kiều Ngọc Anh","DiaChi":"Bến Tre"},"SanPham":{"MaSP":"SP002","TenSP":"Quạt điện","SoLuong":1,"GiaBan":359000,"ThanhTien":359000}}
{"_id":{"$oid":"6672bda5f1b1186875c52aca"},"MaHD":"H001","NgayLap":{"$date":"2020-03-25T00:00:02.007Z"},"KhachHang":{"MaKH":"KH001","TenKH":"Nguyễn Lê Huy","DiaChi":"Bình Phước"},"SanPham":[{"MaSP":"SP004","TenSP":"Nồi cơm điện Panasonic 1","SoLuong":1,"GiaBan":389000,"ThanhTien":389000},{"MaSP":"SP006","TenSP":"Quạt hơi nước dung tích lớn","SoLuong":1,"GiaBan":1370000,"ThanhTien":13700000}]}
{"_id":{"$oid":"6672beb0f1b1186875c52acb"},"MaHD":"H002","NgayLap":{"$date":"2021-01-01T00:00:01.993Z"},"KhachHang":{"MaKH":"KH002","TenKH":"Đào Minh","DiaChi":"Cần Thơ"},"SanPham":{"MaSP":"SP007","TenSP":"Bộ 3 Xoong nồi loại 1 ","SoLuong":1,"GiaBan":245000,"ThanhTien":245000}}
{"_id":{"$oid":"6672beb0f1b1186875c52acc"},"MaHD":"H001","NgayLap":{"$date":"2020-01-21T00:00:02.012Z"},"KhachHang":{"MaKH":"KH001","TenKH":"Minh Hoà","DiaChi":"TP.HCM"},"SanPham":[{"MaSP":"SP004","TenSP":"Nồi cơm điện Panasonic 1","SoLuong":1,"GiaBan":389000,"ThanhTien":389000},{"MaSP":"SP008","TenSP":"Tủ lạnh aqua","SoLuong":1,"GiaBan":4375000,"ThanhTien":43750000}]}
{"_id":{"$oid":"6672bf3df1b1186875c52acd"},"MaHD":"H002","NgayLap":{"$date":"2020-03-25T00:00:01.992Z"},"KhachHang":{"MaKH":"KH002","TenKH":"Chương","DiaChi":"Thủ Đức, TP.HCM"},"SanPham":{"MaSP":"SP007","TenSP":"Bộ 3 Xoong nồi loại 1 ","SoLuong":1,"GiaBan":245000,"ThanhTien":245000}}
{"_id":{"$oid":"6672bf3df1b1186875c52ace"},"MaHD":"H001","NgayLap":{"$date":"2023-06-04T00:00:01.992Z"},"KhachHang":{"MaKH":"KH001","TenKH":"Minh Hoàng","DiaChi":"TP.HCM"},"SanPham":[{"MaSP":"SP004","TenSP":"Nồi cơm điện Panasonic 1","SoLuong":1,"GiaBan":389000,"ThanhTien":389000},{"MaSP":"SP008","TenSP":"Tủ lạnh aqua","SoLuong":1,"GiaBan":4375000,"ThanhTien":43750000}]}
{"_id":{"$oid":"6672bf94f1b1186875c52acf"},"MaHD":"H003","NgayLap":{"$date":"2023-06-06T00:00:01.992Z"},"KhachHang":{"MaKH":"KH003","TenKH":"Phương Trang","DiaChi":"Thủ Đức, TP.HCM"},"SanPham":{"MaSP":"SP007","TenSP":"Bộ 3 Xoong nồi loại 1 ","SoLuong":1,"GiaBan":245000,"ThanhTien":245000}}
{"_id":{"$oid":"6672bf94f1b1186875c52ad0"},"MaHD":"H001","NgayLap":{"$date":"2020-06-09T00:00:01.989Z"},"KhachHang":{"MaKH":"KH001","TenKH":"Huỳnh Thanh Ngân","DiaChi":"TP.HCM"},"SanPham":[{"MaSP":"SP004","TenSP":"Nồi cơm điện Panasonic 1","SoLuong":1,"GiaBan":389000,"ThanhTien":389000},{"MaSP":"SP008","TenSP":"Tủ lạnh aqua","SoLuong":1,"GiaBan":4375000,"ThanhTien":43750000},{"MaSP":"SP006","TenSP":"Quạt hơi nước dung tích lớn","SoLuong":1,"GiaBan":1370000,"ThanhTien":13700000}]}
